griddy/LayoutGenerator.py
griddy/__init__.py
griddy/__main__.py
griddy-0.3.0.dist-info/LICENSE
griddy-0.3.0.dist-info/METADATA
griddy-0.3.0.dist-info/WHEEL
griddy-0.3.0.dist-info/entry_points.txt
griddy-0.3.0.dist-info/top_level.txt
griddy-0.3.0.dist-info/RECORD
