Metadata-Version: 2.1
Name: griddy
Version: 0.3.0
Summary: Generate CSS grid-layouts FAST.
Home-page: https://github.com/Mckinsey666/griddy
Author: Mckinsey666
Author-email: UNKNOWN
License: UNKNOWN
Keywords: html css javascript grid-layouts flexbox
Platform: UNKNOWN
